mp_btp/__init__.py
mp_btp/admin.py
mp_btp/client.py
mp_btp/instance_lock.py
mp_btp/shell.py
mp_btp/api/__init__.py
mp_btp/api/schemas.py
mp_btp/api/server.py
mp_btp/api/routes/__init__.py
mp_btp/api/routes/accounts.py
mp_btp/api/routes/deployments.py
mp_btp/api/routes/health.py
mp_btp/api/routes/kyma.py
mp_btp/api/routes/maintenance.py
mp_btp/api/routes/__pycache__/__init__.cpython-312.pyc
mp_btp/api/routes/__pycache__/accounts.cpython-312.pyc
mp_btp/api/routes/__pycache__/deployments.cpython-312.pyc
mp_btp/api/routes/__pycache__/health.cpython-312.pyc
mp_btp/api/routes/__pycache__/kyma.cpython-312.pyc
mp_btp/api/routes/__pycache__/maintenance.cpython-312.pyc
mp_btp/config/__init__.py
mp_btp/config/config.yaml
mp_btp/integrations/__init__.py
mp_btp/integrations/btp_cli.py
mp_btp/integrations/cf.py
mp_btp/integrations/kyma.py
mp_btp/integrations/multi_node.py
mp_btp/integrations/node_selector.py
mp_btp/integrations/proxy_pool.py
mp_btp/integrations/tool_manager.py
mp_btp/models/__init__.py
mp_btp/models/account.py
mp_btp/models/base.py
mp_btp/models/cf.py
mp_btp/models/database.py
mp_btp/models/deployment.py
mp_btp/models/kyma.py
mp_btp/models/operation_log.py
mp_btp/models/service_instance.py
mp_btp/scheduler/__init__.py
mp_btp/scheduler/cf_pattern.py
mp_btp/scheduler/core.py
mp_btp/tasks/__init__.py
mp_btp/tasks/cleanup.py
mp_btp/tasks/deployment.py
mp_btp/tasks/scheduled.py
mp_btp/utils/__init__.py
mp_btp/utils/audit.py
mp_btp/utils/compose_parser.py
mp_btp/utils/crypto.py
mp_btp-2.1.45.dist-info/METADATA
mp_btp-2.1.45.dist-info/WHEEL
mp_btp-2.1.45.dist-info/entry_points.txt
mp_btp-2.1.45.dist-info/top_level.txt
mp_btp-2.1.45.dist-info/RECORD
