Metadata-Version: 2.4
Name: mp-btp
Version: 2.1.45
Requires-Python: >=3.9
Requires-Dist: fastapi>=0.104.0
Requires-Dist: uvicorn>=0.24.0
Requires-Dist: sqlalchemy>=2.0.0
Requires-Dist: pyyaml>=6.0
Requires-Dist: requests>=2.31.0
Requires-Dist: click>=8.1.0
Requires-Dist: playwright>=1.40.0
Requires-Dist: python-dotenv>=1.0.0
Requires-Dist: pydantic>=2.0.0
Requires-Dist: pydantic-settings>=2.0.0
Requires-Dist: apscheduler>=3.10.0
Requires-Dist: pytz>=2023.3
Requires-Dist: psycopg2-binary>=2.9.0
Dynamic: requires-python
